CHANGELOG.md
LICENSE
MANIFEST.in
README.md
setup.cfg
setup.py
pip_services_container/Component.py
pip_services_container/Container.py
pip_services_container/ProcessContainer.py
pip_services_container/__init__.py
pip_services_container.egg-info/PKG-INFO
pip_services_container.egg-info/SOURCES.txt
pip_services_container.egg-info/dependency_links.txt
pip_services_container.egg-info/requires.txt
pip_services_container.egg-info/top_level.txt
pip_services_container.egg-info/zip-safe
pip_services_container/build/DefaultContainerFactory.py
pip_services_container/build/__init__.py
pip_services_container/config/ComponentConfig.py
pip_services_container/config/ContainerConfig.py
pip_services_container/config/ContainerConfigReader.py
pip_services_container/config/__init__.py
pip_services_container/info/ContainerInfo.py
pip_services_container/info/ContainerInfoFactory.py
pip_services_container/info/__init__.py
pip_services_container/refer/BuildReferencesDecorator.py
pip_services_container/refer/ContainerReferences.py
pip_services_container/refer/LinkReferencesDecorator.py
pip_services_container/refer/ManagedReferences.py
pip_services_container/refer/ReferencesDecorator.py
pip_services_container/refer/RunReferencesDecorator.py
pip_services_container/refer/__init__.py